LICENSE.txt
README.md
setup.cfg
setup.py
Topsis_Tanisha_102203340.egg-info/PKG-INFO
Topsis_Tanisha_102203340.egg-info/SOURCES.txt
Topsis_Tanisha_102203340.egg-info/dependency_links.txt
Topsis_Tanisha_102203340.egg-info/entry_points.txt
Topsis_Tanisha_102203340.egg-info/requires.txt
Topsis_Tanisha_102203340.egg-info/top_level.txt
topsis/102203340.py
topsis/__init__.py